{
  "ResponseId": "R_40YifQ0v0fl2Okh",
  "Q37_feedback_on_work": 1,
  "Q38_1_feedback_helpful_AI": 5,
  "Q38_2_feedback_helpful_teacher": 4,
  "Q39_1_feedback_trust_AI": 4,
  "Q39_2_feedback_trust_teacher": 4,
  "Question 40": {
    "Question": "Please describe any differences in how it impacted your learning (comparing GenAI and your teacher)?",
    "Response": "sometimes tutors don't go into enough detail about a specific part/or don't provide insight into how to fix it whereas AI does.",
    "GoodQuote": "",
    "Codes": [
      {
        "Actor": "T",
        "Comparator": "less",
        "Characteristic": "Specificity"
      }
    ]
  },
  "Question 41": {
    "Question": "Were there any differences in how the feedback made you feel (comparing GenAI and your teacher)?",
    "Response": "maybe its because AI isn't a real human, but I feel like feedback from a tutor feels like being told off, whereas AI feedback is more on how to improve.",
    "GoodQuote": "",
    "Codes": [
      {
        "Actor": "T",
        "Comparator": "more",
        "Characteristic": "Negativity"
      },
      {
        "Actor": "A",
        "Comparator": "more",
        "Characteristic": "No impact"
      }
    ]
  },
  "Question 42": {
    "Question": "Describe any other differences between the feedback you received from GenAI and your teacher.",
    "Response": "AI will usually give you a plethora of feedback and how to implement It. However, feedback from tutors gives more specific feedback as they are the ones who specialise in the content and pick up smaller things that AI doesn't.",
    "GoodQuote": "",
    "Codes": [
      {
        "Actor": "T",
        "Comparator": "more",
        "Characteristic": "Specificity"
      },
      {
        "Actor": "T",
        "Comparator": "more",
        "Characteristic": "Expert"
      }
    ]
  }
}