{
  "ResponseId": "R_4BkzUrnhuruSHBw",
  "Q37_feedback_on_work": 1,
  "Q38_1_feedback_helpful_AI": 4,
  "Q38_2_feedback_helpful_teacher": 5,
  "Q39_1_feedback_trust_AI": 4,
  "Q39_2_feedback_trust_teacher": 4,
  "Question 40": {
    "Question": "Please describe any differences in how it impacted your learning (comparing GenAI and your teacher)?",
    "Response": "feedbacks from teachers are more detailed and more personal",
    "GoodQuote": "",
    "Codes": [
      {
        "Actor": "T",
        "Comparator": "more",
        "Characteristic": "Specificity"
      },
      {
        "Actor": "T",
        "Comparator": "more",
        "Characteristic": "Personal"
      }
    ]
  },
  "Question 41": {
    "Question": "Were there any differences in how the feedback made you feel (comparing GenAI and your teacher)?",
    "Response": "i still got confused time to time when using an AI",
    "GoodQuote": "",
    "Codes": [
      {
        "Actor": "A",
        "Comparator": "less",
        "Characteristic": "Reliable"
      }
    ]
  },
  "Question 42": {
    "Question": "Describe any other differences between the feedback you received from GenAI and your teacher.",
    "Response": "teachers would bring out some other useful suggestions",
    "GoodQuote": "",
    "Codes": [
      {
        "Actor": "T",
        "Comparator": "more",
        "Characteristic": "Utility"
      }
    ]
  }
}