{
  "ResponseId": "R_4CC8GoGU48YmYoG",
  "Q37_feedback_on_work": 1,
  "Q38_1_feedback_helpful_AI": 4,
  "Q38_2_feedback_helpful_teacher": 5,
  "Q39_1_feedback_trust_AI": 4,
  "Q39_2_feedback_trust_teacher": 5,
  "Question 42": {
    "Question": "Describe any other differences between the feedback you received from GenAI and your teacher.",
    "Response": "The feedback from GenAI is not always accurate. I trust the feedback my teacher to give me to be accurate",
    "GoodQuote": "",
    "Codes": [
      {
        "Actor": "A",
        "Comparator": "less",
        "Characteristic": "Reliable"
      },
      {
        "Actor": "T",
        "Comparator": "more",
        "Characteristic": "Reliable"
      }
    ]
  }
}