{
  "ResponseId": "R_4Llk8msiPhkjlsJ",
  "Q37_feedback_on_work": 1,
  "Q38_1_feedback_helpful_AI": 5,
  "Q38_2_feedback_helpful_teacher": 5,
  "Q39_1_feedback_trust_AI": 5,
  "Q39_2_feedback_trust_teacher": 5,
  "Question 40": {
    "Question": "Please describe any differences in how it impacted your learning (comparing GenAI and your teacher)?",
    "Response": "GenAi is straight to the point whereas i find teachers beat around the bush",
    "GoodQuote": "",
    "Codes": [
      {
        "Actor": "A",
        "Comparator": "more",
        "Characteristic": "Understandable"
      },
      {
        "Actor": "T",
        "Comparator": "less",
        "Characteristic": "Understandable"
      }
    ]
  },
  "Question 41": {
    "Question": "Were there any differences in how the feedback made you feel (comparing GenAI and your teacher)?",
    "Response": "none",
    "GoodQuote": "",
    "Codes": [
      {
        "Actor": "Nil"
      }
    ]
  },
  "Question 42": {
    "Question": "Describe any other differences between the feedback you received from GenAI and your teacher.",
    "Response": "genai feedback is broader than my teacher",
    "GoodQuote": "",
    "Codes": [
      {
        "Actor": "A",
        "Comparator": "less",
        "Characteristic": "Specificity"
      }
    ]
  }
}